et_micc2/__init__.py
et_micc2/cli_micc.py
et_micc2/obsolete/config.py
et_micc2/obsolete/db.py
et_micc2/obsolete/expand.py
et_micc2/obsolete/logger.py
et_micc2/obsolete/micc.json
et_micc2/obsolete/project.py
et_micc2/obsolete/static_vars.py
et_micc2/obsolete/utils.py
et_micc2/scripts/install-e.py
et_micc2/subcmds/add.py
et_micc2/subcmds/build.py
et_micc2/subcmds/check_env.py
et_micc2/subcmds/create.py
et_micc2/subcmds/doc.py
et_micc2/subcmds/info.py
et_micc2/subcmds/mv.py
et_micc2/subcmds/tag.py
et_micc2/subcmds/version.py
et_micc2/templates/app-single-command/{{tmpl.project_name}}/tests/{{tmpl.package_name}}/cli/{{tmpl.test_}}{{tmpl.app_name}}.py
et_micc2/templates/app-single-command/{{tmpl.project_name}}/{{tmpl.package_name}}/cli/{{tmpl.app_name}}.py
et_micc2/templates/app-sub-commands/{{tmpl.project_name}}/tests/{{tmpl.package_name}}/cli/{{tmpl.test_}}{{tmpl.app_name}}.py
et_micc2/templates/app-sub-commands/{{tmpl.project_name}}/{{tmpl.package_name}}/cli/{{tmpl.app_name}}.py
et_micc2/templates/submodule-cpp/{{tmpl.module_name}}/CMakeLists.txt
et_micc2/templates/submodule-cpp/{{tmpl.module_name}}/{{tmpl.module_name}}.cpp
et_micc2/templates/submodule-cpp/{{tmpl.module_name}}/{{tmpl.module_name}}.rst
et_micc2/templates/submodule-cpp-test/{{tmpl.module_name}}/test_{{tmpl.module_name}}.py
et_micc2/templates/submodule-f90/{{tmpl.module_name}}/CMakeLists.txt
et_micc2/templates/submodule-f90/{{tmpl.module_name}}/{{tmpl.module_name}}.f90
et_micc2/templates/submodule-f90/{{tmpl.module_name}}/{{tmpl.module_name}}.rst
et_micc2/templates/submodule-f90-test/{{tmpl.module_name}}/test_{{tmpl.module_name}}.py
et_micc2/templates/submodule-py/{{tmpl.module_name}}/__init__.py
et_micc2/templates/submodule-py-test/{{tmpl.module_name}}/{{tmpl.test_}}{{tmpl.module_name}}.py
et_micc2/templates/top-level-package/{{tmpl.project_name}}/.gitignore
et_micc2/templates/top-level-package/{{tmpl.project_name}}/.readthedocs.yml
et_micc2/templates/top-level-package/{{tmpl.project_name}}/API.rst
et_micc2-4.0.0.dist-info/LICENSE
et_micc2-4.0.0.dist-info/METADATA
et_micc2-4.0.0.dist-info/WHEEL
et_micc2-4.0.0.dist-info/entry_points.txt
et_micc2-4.0.0.dist-info/RECORD
