Metadata-Version: 2.1
Name: et-micc2
Version: 4.0.0
Summary: A practical Python project skeleton generator.
Home-page: https://github.com/etijskens/et-micc2
License: MIT
Keywords: project management
Author: Engelbert Tijskens
Author-email: engelbert.tijskens@uantwerpen.be
Requires-Python: >=3.6,<4.0
Classifier: License :: OSI Approved :: MIT License
Classifier: Programming Language :: Python :: 3
Classifier: Programming Language :: Python :: 3.6
Classifier: Programming Language :: Python :: 3.7
Classifier: Programming Language :: Python :: 3.8
Classifier: Programming Language :: Python :: 3.9
Classifier: Programming Language :: Python :: 3.10
Classifier: Programming Language :: Python :: 3.11
Requires-Dist: click (>=7.0,<8.0)
Requires-Dist: pypi-simple (>=0.8.0,<0.9.0)
Requires-Dist: semantic_version (>=2.8.3,<3.0.0)
Requires-Dist: tomlkit (>=0.7.0,<0.8.0)
Requires-Dist: walkdir (>=0.4.1,<0.5.0)
Project-URL: Repository, https://github.com/etijskens/et-micc2
